{"version": 5, "show": {"title": "Agtech - So What?", "summary": null, "poster": "https://feeds.backtracks.fm/feeds/series/a19b8b0e-6913-11ec-800c-0e4caa76571f/images/main.png?1669665018341", "link": "https://www.agtechsowhat.com/"}, "title": "Why You Should Give a F*ck About Farming - Gabrielle Chan", "subtitle": "Why You Should Give a F*ck About Farming - Gabrielle Chan", "summary": "<div>Does the average citizen actually need to care about how their food is produced? This is the central question Australian author and journalist, Gabrielle Chan, set out to answer. Her latest book, \u201cWhy you should give a f*ck about farming\u201d details her firm conclusion that, yes, if you eat food, you should in fact care about agriculture. </div><div><br /></div><div>While the old days of agriculture as the top contributor to GDP are over for most Western countries, Gabrielle argues the future of food and farming is becoming increasingly important for a raft of other reasons such as climate change and food security.</div><div><br /></div><div>In this episode, she talks about:</div><ul><li>Her own introduction to farming, including what shocked her when she first moved from the city to marry a farmer.</li><li>The emergence of \u2018food tribes\u2019, where people view what they eat as part of their identity.</li><li>How politics is failing agriculture by not having a \u201cbackyard plan,\u201d a strategy to value natural capital and make considered decisions about land use.</li><li>The role of agtech in bringing outsiders into agriculture, reinvigorating rural communities, and re-establishing connections between consumers and farmers.</li></ul><div><br /></div><div>For more information and resources, visit our <a href=\"https://www.agtechsowhat.com/\" target=\"_blank\">website</a></div>", "publicationDate": "Wed, 20 Oct 2021 19:01:00 +0000", "duration": "00:39:19", "poster": "https://feeds.backtracks.fm/feeds/series/a19b8b0e-6913-11ec-800c-0e4caa76571f/episodes/f3bbc7b2-6a96-11ec-ae29-0e1130976a5f/images/main.png?1669665031963", "link": "https://www.agtechsowhat.com/agtechsowhatepisodes/2021/10/19/why-you-should-give-a-fck-about-farming", "audio": [{"url": "https://backtracks.fm/tenacious/pr/f3b2f9fc-6a96-11ec-ae29-0e1130976a5f/918135.mp3?s=1&sd=1&u=1640995721", "size": "38052667", "title": "MP3 Audio (mp3)", "mimeType": "audio/mpeg"}], "contributors": null}