{"version": 5, "show": {"title": "Farmerama", "summary": null, "poster": "https://i1.sndcdn.com/avatars-000615700872-y2kyn7-original.jpg", "link": "http://farmerama.co"}, "title": "Shorts: Harvest Barn market Garden June", "subtitle": "Shorts: Harvest Barn market Garden June", "summary": "Regular contributor Joel Rodker is creating a market garden from scratch and recording a diary for Farmerama as he goes. In this report he lets us know what he's been up to during the month of June. Time have been tough but he's enjoying being outside and working in the English summer sun.", "publicationDate": "Sun, 01 Jul 2018 18:52:43 +0000", "duration": "00:06:35", "poster": "https://i1.sndcdn.com/artworks-000367478514-ks89pf-t3000x3000.jpg", "link": "https://soundcloud.com/farmerama-radio/shorts-harvest-barn-market-garden-june", "audio": [{"url": "https://feeds.soundcloud.com/stream/465981132-farmerama-radio-shorts-harvest-barn-market-garden-june.mp3", "size": "6393148", "title": "MP3 Audio (mp3)", "mimeType": "audio/mpeg"}], "contributors": [{"name": "Farmerama"}]}