{"version": 5, "show": {"title": "Farmerama", "summary": null, "poster": "https://i1.sndcdn.com/avatars-000615700872-y2kyn7-original.jpg", "link": "http://farmerama.co"}, "title": "Shorts: Tony Lovell, carbon-canny cattle rancher at Atlas of the Future event", "subtitle": "Shorts: Tony Lovell, carbon-canny cattle rancher at Atlas of the Future event", "summary": "Hear from Tony Lovell in his talk at Atlas of the Futures recent Barcelona event on 'Fixing the Future'. \n\nAtlas of the Future reports, 'by giving the animals a more holistic hook, carbon-canny cattle rancher Tony Lovell, co-founder of SLM Australia Livestock Fund, has raised a whopping $100 million to help to regenerate the billions of hectares of damaged Australian grasslands \u2013 using soil management, biodiversity restoration and grazing techniques: \u201cCows and sheep are just cows and sheep. They are neither good nor bad. The piece most people are missing is how cattle are managed.\u201d'\n\nAtlas of the Future is an online resource of hope, raising the profile of people working for a better future. Check out their recent interview with Dan Barber and the question we put to him about bringing regenerative soil practices to the table: https://atlasofthefuture.org/6-questions-for-a-food-futurehero-dan-barber/", "publicationDate": "Sat, 30 Jun 2018 17:34:34 +0000", "duration": "00:16:19", "poster": "https://i1.sndcdn.com/artworks-000352117044-a9wuhb-t3000x3000.jpg", "link": "https://soundcloud.com/farmerama-radio/shorts-tony-lovell", "audio": [{"url": "https://feeds.soundcloud.com/stream/448463934-farmerama-radio-shorts-tony-lovell.mp3", "size": "15728684", "title": "MP3 Audio (mp3)", "mimeType": "audio/mpeg"}], "contributors": [{"name": "Farmerama"}]}