{"version": 5, "show": {"title": "Farmerama", "summary": null, "poster": "https://i1.sndcdn.com/avatars-000615700872-y2kyn7-original.jpg", "link": "http://farmerama.co"}, "title": "Shorts: Norwich Farmshare introduction", "subtitle": "Shorts: Norwich Farmshare introduction", "summary": "Regular contributor Joel Rodker previously reported for Farmerama on his progress in setting up a market garden from scratch. In 2019 he has moved to working for Norwich Farmshare and is continues to share his experiences.", "publicationDate": "Mon, 12 Aug 2019 11:25:01 +0000", "duration": "00:06:31", "poster": "https://i1.sndcdn.com/artworks-000581210618-rw7f9y-t3000x3000.jpg", "link": "https://soundcloud.com/farmerama-radio/shorts-norwich-farmshare-introduction", "audio": [{"url": "https://feeds.soundcloud.com/stream/664643888-farmerama-radio-shorts-norwich-farmshare-introduction.mp3", "size": "6331708", "title": "MP3 Audio (mp3)", "mimeType": "audio/mpeg"}], "contributors": [{"name": "Farmerama"}]}