{"version": 5, "show": {"title": "Farmerama", "summary": null, "poster": "https://i1.sndcdn.com/avatars-000615700872-y2kyn7-original.jpg", "link": "http://farmerama.co"}, "title": "Shorts: Celebrating #SeedWeek with seed sovereignty champions Katie Hastings and Gerard Miles", "subtitle": "Shorts: Celebrating #SeedWeek with seed sovereignty champions Katie Hastings and Gerard Miles", "summary": "November 18th marks the start of #SeedWeek - a great opportunity to celebrate and raise awareness of local, organic and open pollinated seed. In this special short Katie Hastings, Wales coordinator for the Gaia Foundation\u2019s Seed Sovereignty Programme, takes us on a walk with Gerald Miles, a Welsh organic farmer who recently protested the planting of GM crops by driving his tractor down to London. Katie and Gerald talk about growing black oats, and the work of Llafyr Ni to trial new oat varieties and strengthen seed resilience.\n\nThis short was recorded by Katie Hastings, and produced by Jo Barratt, Hanna Soderlund and Abby Rose.", "publicationDate": "Mon, 18 Nov 2019 17:28:16 +0000", "duration": "00:17:26", "poster": "https://i1.sndcdn.com/artworks-000639152101-11n6jv-t3000x3000.jpg", "link": "https://soundcloud.com/farmerama-radio/gaia-fondation-black-oats", "audio": [{"url": "https://feeds.soundcloud.com/stream/714247732-farmerama-radio-gaia-fondation-black-oats.mp3", "size": "16803675", "title": "MP3 Audio (mp3)", "mimeType": "audio/mpeg"}], "contributors": [{"name": "Farmerama"}]}